interlogue/__init__.py
interlogue/mind.py
interlogue-0.0.1.dist-info/METADATA
interlogue-0.0.1.dist-info/WHEEL
interlogue-0.0.1.dist-info/licenses/LICENSE
interlogue-0.0.1.dist-info/RECORD
